pygrammar/__init__.py
pygrammar/pygrammar.py
pygrammar-0.0.2.dist-info/LICENSE
pygrammar-0.0.2.dist-info/METADATA
pygrammar-0.0.2.dist-info/WHEEL
pygrammar-0.0.2.dist-info/top_level.txt
pygrammar-0.0.2.dist-info/RECORD
