Metadata-Version: 2.1
Name: pygrammar
Version: 0.0.2
Summary: A package to create number patterns.
Home-page: https://github.com/modfivelabs/pygrammar
Author: ModfiveLabs
Author-email: modfivelabs@gmail.com
Project-URL: Bug Tracker, https://github.com/modfivelabs/pygrammar/issues
Classifier: Programming Language :: Python :: 3
Classifier: License :: OSI Approved :: MIT License
Classifier: Operating System :: OS Independent
Requires-Python: >=3
License-File: LICENSE
